COPYING
MANIFEST.in
README.md
pyproject.toml
setup.cfg
setup.py
msgpack_sorted/__init__.py
msgpack_sorted/_cmsgpack.cpp
msgpack_sorted/_cmsgpack.pyx
msgpack_sorted/_packer.pyx
msgpack_sorted/_unpacker.pyx
msgpack_sorted/buff_converter.h
msgpack_sorted/exceptions.py
msgpack_sorted/ext.py
msgpack_sorted/fallback.py
msgpack_sorted/pack.h
msgpack_sorted/pack_template.h
msgpack_sorted/sysdep.h
msgpack_sorted/unpack.h
msgpack_sorted/unpack_define.h
msgpack_sorted/unpack_template.h
msgpack_sorted.egg-info/PKG-INFO
msgpack_sorted.egg-info/SOURCES.txt
msgpack_sorted.egg-info/dependency_links.txt
msgpack_sorted.egg-info/top_level.txt
test/test_buffer.py
test/test_case.py
test/test_except.py
test/test_extension.py
test/test_format.py
test/test_limits.py
test/test_memoryview.py
test/test_newspec.py
test/test_obj.py
test/test_pack.py
test/test_read_size.py
test/test_seq.py
test/test_sequnpack.py
test/test_stricttype.py
test/test_subtype.py
test/test_timestamp.py
test/test_unpack.py