Metadata-Version: 2.1
Name: msgpack-sorted
Version: 1.0.5
Summary: MessagePack serializer
Home-page: https://msgpack.org/
Author: Inada Naoki, Yaakov Belch
Author-email: yaakov.belch@gmail.com
License: Apache 2.0
Project-URL: Documentation, https://msgpack-python.readthedocs.io/
Project-URL: Source, https://github.com/Yaakov-Belch/msgpack-sorted-python
Project-URL: Tracker, https://github.com/Yaakov-Belch/msgpack-sorted-python/issues
Classifier: Programming Language :: Python :: 3
Classifier: Programming Language :: Python :: 3.8
Classifier: Programming Language :: Python :: 3.9
Classifier: Programming Language :: Python :: 3.10
Classifier: Programming Language :: Python :: 3.11
Classifier: Programming Language :: Python :: 3.12
Classifier: Programming Language :: Python :: Implementation :: CPython
Classifier: Programming Language :: Python :: Implementation :: PyPy
Classifier: Intended Audience :: Developers
Classifier: License :: OSI Approved :: Apache Software License
License-File: COPYING
